gmlutil/__init__.py
gmlutil/config.py
gmlutil/data_cleaning.py
gmlutil/data_extraction.py
gmlutil/feature_engineering.py
gmlutil/map_functions.py
gmlutil/non_timeseries_models.py
gmlutil/timeseries_models.py
gmlutil-1.0.1.dist-info/METADATA
gmlutil-1.0.1.dist-info/WHEEL
gmlutil-1.0.1.dist-info/top_level.txt
gmlutil-1.0.1.dist-info/RECORD
