Metadata-Version: 2.1
Name: gmlutil
Version: 1.0.1
Summary: General Machine Learning Utility Package
Home-page: https://github.com/Phillip1982/gmlutil
Author: Phillip Kim
Author-email: phillip.kim@ejgallo.com
License: BSD 2-clause
Platform: UNKNOWN
Classifier: Development Status :: 5 - Production/Stable
Classifier: Framework :: IPython
Classifier: Intended Audience :: Developers
Classifier: License :: OSI Approved :: BSD License
Classifier: Operating System :: MacOS
Classifier: Operating System :: Microsoft :: Windows :: Windows XP
Classifier: Operating System :: POSIX :: Linux
Classifier: Programming Language :: Python :: 3
Classifier: Programming Language :: Python :: 3.8
Classifier: Programming Language :: Python :: 3.9
Requires-Dist: aiobotocore (==2.5.0)
Requires-Dist: awscli (==1.27.76)
Requires-Dist: boto3 (==1.26.76)
Requires-Dist: botocore (==1.29.76)
Requires-Dist: dash (>=2.0.0)
Requires-Dist: datetime (>=4.3)
Requires-Dist: evidently (>=0.4.8)
Requires-Dist: fastapi (>=0.100.0)
Requires-Dist: fastapi-restful (>=0.5.0)
Requires-Dist: folium (>=0.14.0)
Requires-Dist: fuzzywuzzy (>=0.18.0)
Requires-Dist: geopandas (>=0.10.2)
Requires-Dist: hana-ml
Requires-Dist: imbalanced-learn (>=0.8.0)
Requires-Dist: iterative-telemetry (>=0.0.5)
Requires-Dist: jupyter-dash (>=0.4.0)
Requires-Dist: kmodes (>=0.11.0)
Requires-Dist: nltk (>=3.6.7)
Requires-Dist: numpy (<1.23.0,>=1.19.5)
Requires-Dist: oracledb (>=1.4.2)
Requires-Dist: pandas (<1.4.3,>=1.3.5)
Requires-Dist: packaging (>=21.3)
Requires-Dist: plotly (>=5.5.0)
Requires-Dist: psycopg2-binary (>=2.9.1)
Requires-Dist: pyarrow (<11.0dev)
Requires-Dist: pydantic (<2)
Requires-Dist: pyhdb (>=0.3.4)
Requires-Dist: pymssql (>=2.2.1)
Requires-Dist: pytest-astropy
Requires-Dist: python-levenshtein-wheels (>=0.13.1)
Requires-Dist: pytrends (>=4.7.3)
Requires-Dist: PyYAML (>=5.1)
Requires-Dist: redshift-connector (>=2.0.916)
Requires-Dist: requests (>=2.21.0)
Requires-Dist: rich (>=13)
Requires-Dist: rsa (<4.8,>=3.1.2)
Requires-Dist: sagemaker (==2.0.0)
Requires-Dist: sagemaker-data-insights (==0.3.0)
Requires-Dist: scikit-learn (>=0.24.0)
Requires-Dist: scipy (>=1.5.4)
Requires-Dist: seaborn (>=0.11.2)
Requires-Dist: sparkmagic (>=0.20.4)
Requires-Dist: sqlalchemy-redshift (>=0.8.6)
Requires-Dist: statsmodels (>=0.12.2)
Requires-Dist: s3transfer (>=0.6.0)
Requires-Dist: typer (>=0.3)
Requires-Dist: typing-extensions (>=4.0)
Requires-Dist: typing-inspect (>=0.9.0)
Requires-Dist: uvicorn (>=0.22.0)
Requires-Dist: watchdog (>=3)
Requires-Dist: xgboost (>=1.7.3)
